<OutOfBrowserSettings ShortName="Floating Legs" EnableGPUAcceleration="False" ShowInstallMenuItem="False">
  <OutOfBrowserSettings.Blurb>Floating Legs</OutOfBrowserSettings.Blurb>
  <OutOfBrowserSettings.WindowSettings>
    <WindowSettings Title="Floating Legs" />
  </OutOfBrowserSettings.WindowSettings>
  <OutOfBrowserSettings.SecuritySettings>
    <SecuritySettings ElevatedPermissions="Required" />
  </OutOfBrowserSettings.SecuritySettings>
  <OutOfBrowserSettings.Icons />
</OutOfBrowserSettings>